fzf/__init__.py
fzf/__main__.py
fzf/_fzf.py
fzf/_version.py
fzf/py.typed
typedfzf-1.0.5.dist-info/METADATA
typedfzf-1.0.5.dist-info/WHEEL
typedfzf-1.0.5.dist-info/entry_points.txt
typedfzf-1.0.5.dist-info/licenses/LICENSE.txt
typedfzf-1.0.5.dist-info/RECORD
